napari_time_slicer/__init__.py
napari_time_slicer/_function.py
napari_time_slicer/_workflow.py
napari_time_slicer/_tests/__init__.py
napari_time_slicer/_tests/test_function.py
napari_time_slicer-0.5.0.dist-info/LICENSE
napari_time_slicer-0.5.0.dist-info/METADATA
napari_time_slicer-0.5.0.dist-info/WHEEL
napari_time_slicer-0.5.0.dist-info/entry_points.txt
napari_time_slicer-0.5.0.dist-info/top_level.txt
napari_time_slicer-0.5.0.dist-info/RECORD
