Metadata-Version: 2.1
Name: napari-time-slicer
Version: 0.5.0
Summary: A meta plugin for processing timelapse data in napari timepoint by timepoint
Home-page: https://github.com/haesleinhuepf/napari-time-slicer
Author: Robert Haase
Author-email: robert.haase@tu-dresden.de
License: BSD-3-Clause
Project-URL: Bug Tracker, https://github.com/haesleinhuepf/napari-time-slicer/issues
Project-URL: Documentation, https://github.com/haesleinhuepf/napari-time-slicer#README.md
Project-URL: Source Code, https://github.com/haesleinhuepf/napari-time-slicer
Project-URL: User Support, https://github.com/haesleinhuepf/napari-time-slicer/issues
Classifier: Development Status :: 3 - Alpha
Classifier: Intended Audience :: Developers
Classifier: Framework :: napari
Classifier: Topic :: Scientific/Engineering :: Image Processing
Classifier: Programming Language :: Python
Classifier: Programming Language :: Python :: 3
Classifier: Programming Language :: Python :: 3.8
Classifier: Programming Language :: Python :: 3.9
Classifier: Programming Language :: Python :: 3.10
Classifier: Operating System :: OS Independent
Classifier: License :: OSI Approved :: BSD License
Requires-Python: >=3.8
License-File: LICENSE
Requires-Dist: napari-plugin-engine >=0.1.4
Requires-Dist: numpy
Requires-Dist: toolz
Requires-Dist: napari-tools-menu
Requires-Dist: napari-workflows
